_swmm5.cp311-win_amd64.pyd
swmm5/__init__.py
swmm5/swmm5.py
swmm5/swmm5tools.py
swmm5/tmp.py
swmm5/examples/simple/swmm5Example.inp
SWMM5-5.2.4.dist-info/METADATA
SWMM5-5.2.4.dist-info/WHEEL
SWMM5-5.2.4.dist-info/top_level.txt
SWMM5-5.2.4.dist-info/RECORD
