Metadata-Version: 2.1
Name: SWMM5
Version: 5.2.4
Summary: SWMM5  calls from python
Home-page: http://assela.pathirana.net/SWMM5-Python
Author: Assela Pathirana
Author-email: assela@pathirana.net
License: GNU General Public License version 3
Keywords: Hydraulics,Hydrology,Urban Drainage,Sewerage,Water Engineering,Numerical Methods,Computer Model,Environmental Science,Engineering,Science
Classifier: Programming Language :: Python
Classifier: Programming Language :: Python :: 2.7
Classifier: Environment :: Other Environment
Classifier: Intended Audience :: Education
Classifier: Intended Audience :: Developers
Classifier: Intended Audience :: Science/Research
Classifier: License :: OSI Approved :: GNU General Public License v3 (GPLv3)
Classifier: Operating System :: POSIX
Classifier: Operating System :: Microsoft :: Windows
Classifier: Operating System :: MacOS :: MacOS X
Classifier: Topic :: Software Development :: Libraries :: Python Modules
Classifier: Development Status :: 5 - Production/Stable
Classifier: Natural Language :: English
